LICENSE
README.md
setup.py
NamedEntityRecognition/AutoNER.py
NamedEntityRecognition/Gazetteer.py
NamedEntityRecognition/NERCorpus.py
NamedEntityRecognition/NamedEntitySentence.py
NamedEntityRecognition/NamedEntityType.py
NamedEntityRecognition/NamedEntityWord.py
NamedEntityRecognition/Slot.py
NamedEntityRecognition/SlotType.py
NamedEntityRecognition/__init__.py
NamedEntityRecognition/data/__init__.py
NamedEntityRecognition/data/gazetteer-location.txt
NamedEntityRecognition/data/gazetteer-organization.txt
NamedEntityRecognition/data/gazetteer-person.txt
NlpToolkit_NamedEntityRecognition.egg-info/PKG-INFO
NlpToolkit_NamedEntityRecognition.egg-info/SOURCES.txt
NlpToolkit_NamedEntityRecognition.egg-info/dependency_links.txt
NlpToolkit_NamedEntityRecognition.egg-info/requires.txt
NlpToolkit_NamedEntityRecognition.egg-info/top_level.txt