Metadata-Version: 2.1
Name: NlpToolkit-NamedEntityRecognition
Version: 1.0.10
Summary: NER Corpus Processing Library
Home-page: https://github.com/StarlangSoftware/TurkishNamedEntityRecognition-Py
Author: olcaytaner
Author-email: olcay.yildiz@ozyegin.edu.tr
License: UNKNOWN
Platform: UNKNOWN
License-File: LICENSE
